{
    "200_Yojana": "Item Shit",
    "200_Yojana_1": "Item Shit",
    "ACT_the_FOOL": "Personal Skills",
    "Agnostic": "Statuses",
    "AncientDuper": "Spell Cards",
    "AntiMagAura": "Class Skills",
    "AntiPhysAura": "Class Skills",
    "Anticrit": "Item Shit",
    "Apparitions_That_Stalk_The_Night": "Personal Skills",
    "Avoid10": "Statuses",
    "Ballista_Anim": "Item Shit",
    "Bangasa_Bombing_Run": "Personal Skills",
    "Bangasa_Bombing_Run_1": "Personal Skills",
    "Barrier_Warp": "Personal Skills",
    "Berserk": "Statuses",
    "Beyond_Breaking_Point": "Personal Skills",
    "Beyond_Breaking_Point_1": "Personal Skills",
    "Big_Power_Shot": "Personal Skills",
    "Big_Power_Shot_1": "Personal Skills",
    "Blade_Dance": "Personal Skills",
    "Blazing_Frostflare": "Personal Skills",
    "Blazing_Frostflare_1": "Personal Skills",
    "Bleeding": "Statuses",
    "Bleeding_Shot": "Generic Skills",
    "Bleeding_Shot_Effect": "Generic Skills",
    "Bleeding_Strike": "Item Shit",
    "Bleeding_Strike_1": "Item Shit",
    "Blizzard": "Spell Cards",
    "BlizzardAura": "Personal Skills",
    "Bloodlust": "Personal Skills",
    "Bloodsucker": "Personal Skills",
    "Bloodsucker_Effect": "Personal Skills",
    "Bloodsucker_Effect_1": "Personal Skills",
    "Bloodsucker_Effect_2": "Personal Skills",
    "BulletSign": "Spell Cards",
    "Bulwark": "Statuses",
    "Bumbling_Dodge": "Personal Skills",
    "Burning": "Statuses",
    "Canine_Dash": "Personal Skills",
    "Canine_Dash_1": "Personal Skills",
    "Canto": "Class Skills",
    "Capricious_Cheerleader": "Personal Skills",
    "Certain_Blow": "Generic Skills",
    "Certain_Blow_Effect": "Generic Skills",
    "Chilled": "Statuses",
    "Chopping_Smash": "Generic Skills",
    "Chopping_Smash_Effect": "Generic Skills",
    "Controller_of_Fate": "Personal Skills",
    "Cooldown": "Personal Skills",
    "Crit_Plus15": "Class Skills",
    "Crit_Plus30": "Class Skills",
    "Crit_plus": "Item Shit",
    "Crit_plus_1": "Item Shit",
    "Crush_Blade": "Generic Skills",
    "Crush_Blade_Effect": "Generic Skills",
    "Dagon_Curse": "Statuses",
    "Dagon_Melee_Skill": "Item Shit",
    "Dark_Tome_Anim": "Item Shit",
    "DarknessSign": "Spell Cards",
    "DartingNightjars": "Spell Cards",
    "Decreasing_Work_Efficiency": "Statuses",
    "Dendro": "Statuses",
    "Density": "Personal Skills",
    "Devastator_Strike": "Item Shit",
    "Devastator_Strike_1": "Item Shit",
    "Devil_Luck": "Item Shit",
    "Devil_Luck_1": "Item Shit",
    "Dewdrop_Barrier": "Personal Skills",
    "DollComponent": "Personal Skills",
    "Doll_Coordination": "Personal Skills",
    "Doll_Coordination_1": "Personal Skills",
    "DreamSlicer": "Spell Cards",
    "Dream_Slicer": "Personal Skills",
    "Eclipse_Helper": "Item Shit",
    "Enstrengthened": "Statuses",
    "Eternal_Future": "Item Shit",
    "Eternal_Future_1": "Item Shit",
    "Everwinter_Snowstorm": "Personal Skills",
    "Exhausted": "Statuses",
    "Extreme_Edge": "Generic Skills",
    "Extreme_Edge_Effect": "Generic Skills",
    "Eye_of_Bullshit": "Statuses",
    "FeelingLucky": "Statuses",
    "Flaming_Forward": "Generic Skills",
    "Flaming_Forward_Effect": "Generic Skills",
    "Fleetfoot_Whack": "Generic Skills",
    "Fleetfoot_Whack_Effect": "Generic Skills",
    "Fleetfooted": "Statuses",
    "Flier_Protection": "Item Shit",
    "Flighty_Helper": "Personal Skills",
    "Flood_of_Frost": "Personal Skills",
    "Flood_of_Frost_Art": "Personal Skills",
    "Flying": "Class Skills",
    "FlyingHead": "Spell Cards",
    "Forest": "Statuses",
    "Forgemaster": "Personal Skills",
    "Forgemaster_1": "Personal Skills",
    "Forgemaster_2": "Personal Skills",
    "Forgemaster_3": "Personal Skills",
    "Fort": "Statuses",
    "Friction_Shift": "Statuses",
    "Frost_Barrier": "Statuses",
    "Frosty_Chop": "Generic Skills",
    "Frosty_Chop_Effect": "Generic Skills",
    "Frozen": "Statuses",
    "Frozen_1": "Statuses",
    "Fugue_Tuning": "Personal Skills",
    "Fulmination_Infusion": "Generic Skills",
    "Fulmination_Infusion_Effect": "Generic Skills",
    "GML": "Personal Skills",
    "GML_1": "Personal Skills",
    "Gale_Sweep": "Generic Skills",
    "Gale_Sweep_Effect": "Generic Skills",
    "Gallant_Thrust": "Generic Skills",
    "Gallant_Thrust_Effect": "Generic Skills",
    "Gamble": "Generic Skills",
    "Gamble_Effect": "Generic Skills",
    "GasMaskBonus": "Item Shit",
    "GatheringofSouls": "Personal Skills",
    "Geo": "Statuses",
    "GoneMad": "Spell Cards",
    "Great_Fortune": "Personal Skills",
    "Great_Funeral_Concert": "Personal Skills",
    "Great_Funeral_Concert_1": "Personal Skills",
    "Guardian": "Statuses",
    "Hakurei_Boxing_Higi": "Item Shit",
    "Hakurei_Boxing_Higi_1": "Item Shit",
    "HalfBody": "Item Shit",
    "HalfBody1": "Item Shit",
    "Haphazard_Smash": "Personal Skills",
    "Hard_Worker": "Personal Skills",
    "Head_Distraction": "Personal Skills",
    "Head_Distraction_Effect": "Statuses",
    "HerculesBeetle": "Spell Cards",
    "Homing_Shot": "Personal Skills",
    "Homing_ShotAttack": "Personal Skills",
    "Honshu_Slashing": "Personal Skills",
    "Hydro": "Statuses",
    "Illuminate": "Personal Skills",
    "Illuminate_Effect": "Personal Skills",
    "Immortal_Red_Soul": "Personal Skills",
    "Immortal_Red_Soul_1": "Personal Skills",
    "In_An_Instant": "Personal Skills",
    "Indomitable_Spirit": "Personal Skills",
    "Indomitable_Spirit_1": "Personal Skills",
    "Indomitable_Spirit_2": "Personal Skills",
    "Infest": "Personal Skills",
    "Infest_1": "Personal Skills",
    "Infest_Effect": "Personal Skills",
    "Infest_Effect_1": "Statuses",
    "Instinct_Versus_Desire": "Personal Skills",
    "Instinct_Versus_Desire_1": "Personal Skills",
    "Interfering_Waves": "Personal Skills",
    "Jack_The_Ripper": "Personal Skills",
    "Joule": "Spell Cards",
    "Knowledge_is_Power": "Personal Skills",
    "Knowledge_is_Power_Effect": "Statuses",
    "KusanagiGrowths": "Item Shit",
    "KusanagiGrowths_1": "Item Shit",
    "KusanagiGrowths_2": "Item Shit",
    "KusanagiGrowths_3": "Item Shit",
    "Kusanagi_Gold": "Item Shit",
    "LanternBonus": "Item Shit",
    "Lethal_Life_Flow": "Personal Skills",
    "Lethal_Life_Flow1": "Personal Skills",
    "Light_Refract": "Personal Skills",
    "Light_Tome_Anim": "Item Shit",
    "Lightspeed_Flash": "Generic Skills",
    "Lightspeed_Flash_Effect": "Generic Skills",
    "LockdownZone": "Spell Cards",
    "LockdownZoneAura": "Personal Skills",
    "LockdownZoneAura_1": "Personal Skills",
    "Looter": "Class Skills",
    "Luna_Dial": "Personal Skills",
    "Luna_Dial_1": "Personal Skills",
    "Lunar": "Statuses",
    "LunaticSeptember": "Spell Cards",
    "Lunatic_Haze_on_Bloody_Battlefield": "Personal Skills",
    "Lunatic_Red_Eyes": "Personal Skills",
    "Lunatic_Red_Eyes_1": "Personal Skills",
    "Lunatic_Red_Eyes_Effect": "Statuses",
    "Magic_Miasma": "Class Skills",
    "Magical_Flux": "Statuses",
    "Magical_Might": "Personal Skills",
    "Magithief": "Item Shit",
    "MakaiSynchrogazer": "Spell Cards",
    "Makai_Overdrive": "Statuses",
    "Mana_Overcharge": "Generic Skills",
    "Mana_Overcharge_Effect": "Generic Skills",
    "MarkedForDeath": "Personal Skills",
    "Mask_Anger": "Personal Skills",
    "Mask_Calm": "Personal Skills",
    "Mask_Change": "Personal Skills",
    "Mask_Happy": "Personal Skills",
    "Mask_Hope": "Personal Skills",
    "Mask_Hope2": "Personal Skills",
    "Mask_Sad": "Personal Skills",
    "Master_Pharmacist": "Personal Skills",
    "Mercy": "Personal Skills",
    "MercyAura": "Personal Skills",
    "Mercy_Art": "Personal Skills",
    "Metallic": "Statuses",
    "Mogu_Mogu": "Personal Skills",
    "Moonbow": "Generic Skills",
    "Moonbow_Effect": "Generic Skills",
    "Motivated": "Personal Skills",
    "Mountain": "Statuses",
    "NPCStatus": "Class Skills",
    "Nameless_City": "Personal Skills",
    "Natural_Talent": "Personal Skills",
    "Nature_Power": "Personal Skills",
    "Newton": "Spell Cards",
    "Night_Blinder": "Generic Skills",
    "Night_Blinder_Effect": "Generic Skills",
    "Night_Hunter": "Statuses",
    "NightjarAura": "Personal Skills",
    "NightjarAura_1": "Personal Skills",
    "NoAvoid": "Class Skills",
    "NoAxe": "Personal Skills",
    "NoBow": "Personal Skills",
    "NoFatigue": "Personal Skills",
    "NoKnife": "Personal Skills",
    "NoLance": "Personal Skills",
    "NoMartial": "Personal Skills",
    "NoSelect": "Class Skills",
    "NoSword": "Personal Skills",
    "No_Cheating": "Statuses",
    "Opening_Wound": "Personal Skills",
    "Optimism": "Personal Skills",
    "Orreries_Solar_System": "Personal Skills",
    "Overwhelm": "Generic Skills",
    "Overwhelm_Effect": "Generic Skills",
    "Paralyzing_Chant": "Personal Skills",
    "Paralyzing_Chant_Effect": "Personal Skills",
    "Paralyzing_Chant_Effect_1": "Personal Skills",
    "Paralyzing_Chant_Effect_2": "Personal Skills",
    "Parry": "Item Shit",
    "Parry_Effect": "Item Shit",
    "Peak": "Statuses",
    "Perfect_Freeze": "Personal Skills",
    "Perfect_Freeze_Art": "Personal Skills",
    "Perfect_Shot": "Generic Skills",
    "Perfect_Shot_Effect": "Generic Skills",
    "Petrify": "Statuses",
    "Phoenix_Aura": "Personal Skills",
    "Phoenix_Aura_1": "Personal Skills",
    "Phoenix_Crash": "Personal Skills",
    "Pivot": "Personal Skills",
    "Poison_Strike": "Item Shit",
    "Poison_Strike_1": "Item Shit",
    "Poisoned": "Statuses",
    "Portal_Combat": "Personal Skills",
    "PowerStrike": "Item Shit",
    "Power_Shot": "Generic Skills",
    "Power_Shot_Effect": "Generic Skills",
    "Prism_Camouflage": "Personal Skills",
    "Protected": "Item Shit",
    "Puppet_Assault": "Personal Skills",
    "PuppeteersMark": "Statuses",
    "Purifying_Sutra": "Generic Skills",
    "Purifying_Sutra_Effect": "Generic Skills",
    "Pyro": "Statuses",
    "Quick_Counter": "Personal Skills",
    "Quiet_Aura": "Statuses",
    "ReactionaryStance": "Personal Skills",
    "Recoil_Arson": "Item Shit",
    "Recoil_Elfire": "Item Shit",
    "Recoil_Fire": "Item Shit",
    "RedHarvest": "Personal Skills",
    "RedHarvest_1": "Personal Skills",
    "Reflect_Slash": "Item Shit",
    "Reflect_Slash1": "Item Shit",
    "Requiem_Tuning": "Personal Skills",
    "Rescue": "Statuses",
    "ResistPlus": "Item Shit",
    "Revelry_Tuning": "Personal Skills",
    "Rin_Satsuki": "Personal Skills",
    "Rushdown": "Generic Skills",
    "Rushdown_Effect": "Generic Skills",
    "Saigyou_Wind": "Item Shit",
    "Saigyou_Wind_1": "Item Shit",
    "Saigyou_Wind_2": "Personal Skills",
    "SamidareBroiler": "Spell Cards",
    "SamidareBroiler_1": "Spell Cards",
    "Scattered_Flowers": "Item Shit",
    "Scattered_Flowers1": "Item Shit",
    "ScreamOut": "Personal Skills",
    "ScreamOut_1": "Personal Skills",
    "Searchlight": "Personal Skills",
    "Searchlight_1": "Statuses",
    "Sharpshooter": "Personal Skills",
    "Shattering_Moon": "Personal Skills",
    "Shattering_Moon_Effect": "Personal Skills",
    "Shock": "Statuses",
    "Shrine_Power": "Personal Skills",
    "Shrine_Power_Boost": "Personal Skills",
    "Shuraken1": "Spell Cards",
    "Shuraken2": "Spell Cards",
    "Shuraken3": "Spell Cards",
    "Silence": "Statuses",
    "Silence_1": "Statuses",
    "Sleep": "Statuses",
    "Slime_Melee_Skill": "Item Shit",
    "Sniper": "Personal Skills",
    "Solar": "Statuses",
    "SolarSystem": "Spell Cards",
    "Sparrow_Song": "Personal Skills",
    "Spear_The_Gungnir": "Personal Skills",
    "Spear_The_Gungnir_1": "Personal Skills",
    "Spear_Throw": "Generic Skills",
    "Spear_Throw_Effect": "Generic Skills",
    "Staking_Your_Life_on_a_Prank": "Personal Skills",
    "Star_Laser": "Personal Skills",
    "Star_LaserAttack": "Personal Skills",
    "Stoneskinned": "Personal Skills",
    "Stoneskinned1": "Personal Skills",
    "Stoneskinned2": "Personal Skills",
    "Stoneskinned_Status": "Statuses",
    "String_Commander": "Personal Skills",
    "Stunned": "Statuses",
    "Sudden_Upset": "Item Shit",
    "Summoning_Sickness": "Statuses",
    "Super_Luck": "Personal Skills",
    "Swift_Hunter": "Personal Skills",
    "Swift_Jab": "Generic Skills",
    "Swift_Jab_Effect": "Generic Skills",
    "Taskmaster": "Personal Skills",
    "Taskmaster_Effect": "Statuses",
    "Temporal_Shift": "Personal Skills",
    "The_Eternity": "Personal Skills",
    "The_Strongest": "Personal Skills",
    "Thick_Fur": "Personal Skills",
    "Thick_Fur_Part2": "Personal Skills",
    "Thief": "Class Skills",
    "Throne": "Statuses",
    "Thunder_Tome_Anim": "Item Shit",
    "TindalosEffect": "Item Shit",
    "Tired": "Personal Skills",
    "Torch": "Item Shit",
    "Tough_Carapace": "Personal Skills",
    "Tough_Claws": "Generic Skills",
    "Tough_Claws_Effect": "Generic Skills",
    "TourGuide": "Spell Cards",
    "TriadofMagic": "Spell Cards",
    "Undead": "Class Skills",
    "Vanished": "Personal Skills",
    "Vantage": "Personal Skills",
    "Vengeful_Spirit": "Personal Skills",
    "Void_Curse": "Statuses",
    "Warp_Kingdom": "Personal Skills",
    "Weakened": "Statuses",
    "Weakened_1": "Statuses",
    "Whirlwind_Strike": "Item Shit",
    "Whirlwind_Strike_1": "Item Shit",
    "Wild_Claw": "Item Shit",
    "Wind_Shear": "Statuses",
    "Witch_Warp_Test": "Personal Skills",
    "WolfSign": "Spell Cards",
    "Wolf_Fang": "Personal Skills",
    "Wolf_Fang_1": "Personal Skills",
    "Wolf_Fang_Proc": "Personal Skills",
    "Yataderas_Gift": "Personal Skills",
    "Yomi_Melee_Skill": "Item Shit",
    "Zip_Bomb": "Personal Skills",
    "ankh": "Item Shit",
    "eyeofsenri_1": "Item Shit",
    "forged_shield": "Item Shit",
    "growths_robe": "Item Shit",
    "growths_stone": "Item Shit",
    "kappatech_shield": "Item Shit",
    "magic_shield_check": "Item Shit",
    "maple_shield": "Item Shit",
    "misfortune_amulet": "Item Shit",
    "new": "Statuses",
    "poppet": "Item Shit",
    "poppet_2": "Item Shit",
    "shield_check": "Item Shit",
    "shield_check_1": "Item Shit"
}