[
    {
        "nid": "Rumia_Boss",
        "name": "Rumia",
        "desc": "The youkai of darkness. Eats humans, but doesn't bother hunting them. Not the brightest.",
        "variant": null,
        "level": 5,
        "klass": "Shaman",
        "tags": [
            "Boss"
        ],
        "bases": {
            "HP": 25,
            "STR": 3,
            "MAG": 8,
            "SKL": 4,
            "SPD": 3,
            "CON": 7,
            "DEF": 7,
            "RES": 4,
            "LCK": 5,
            "MOV": 0
        },
        "growths": {
            "DEF": 50,
            "SPD": 30,
            "MOV": 0,
            "STR": 50,
            "SKL": 45,
            "LCK": 35,
            "RES": 25,
            "HP": 80,
            "CON": 0,
            "MAG": 45
        },
        "stat_cap_modifiers": {
            "DEF": 0,
            "SPD": 0,
            "MOV": 0,
            "STR": 0,
            "SKL": 0,
            "LCK": 0,
            "RES": 0,
            "HP": 0,
            "CON": 0,
            "MAG": 0
        },
        "starting_items": [
            [
                "Flux",
                false
            ],
            [
                "Life_Gem",
                true
            ]
        ],
        "learned_skills": [],
        "unit_notes": [],
        "wexp_gain": {
            "Dark": [
                false,
                31,
                null
            ]
        },
        "alternate_classes": [],
        "portrait_nid": "rumia",
        "affinity": "Light",
        "fields": []
    }
]