[
    {
        "nid": "Eternal_Future_1",
        "name": "Slash of the Eternal Future",
        "desc": "Youmu unleashes one uncounterable slash that doubles her strength and +50 Crit Rate at -30% hit. \nCost: 5 Durability",
        "icon_nid": "NewIcon1",
        "icon_index": [
            0,
            2
        ],
        "components": [
            [
                "hit",
                -30
            ],
            [
                "crit",
                50
            ],
            [
                "item_override",
                "new"
            ]
        ]
    }
]