[
    {
        "nid": "Scattered_Flowers1",
        "name": "Flashing Scattered Flowers",
        "desc": "Youmu enters scattered stance, removing her ability to counter at all but raising her avoid by 50% when defending. ",
        "icon_nid": "NewIcon1",
        "icon_index": [
            0,
            4
        ],
        "components": [
            [
                "time",
                1
            ],
            [
                "item_override",
                "new_3"
            ],
            [
                "avoid",
                50
            ],
            [
                "combat_condition",
                "mode != 'attack'"
            ]
        ]
    }
]