[
    {
        "nid": "DEBUG_1",
        "name": "DEBUG",
        "tilemap": "Debug",
        "bg_tilemap": null,
        "party": "Reimu",
        "music": {
            "player_phase": "Quiet Burn",
            "enemy_phase": "Quiet Burn",
            "other_phase": null,
            "enemy2_phase": null,
            "player_battle": "Quiet Burn",
            "enemy_battle": "Quiet Burn",
            "other_battle": null,
            "enemy2_battle": null,
            "boss_battle": "Dullahan Under the Willows"
        },
        "objective": {
            "simple": "{v:_random_seed}",
            "win": "Don't Crash",
            "loss": "Crash"
        },
        "roam": false,
        "roam_unit": null,
        "go_to_overworld": false,
        "should_record": true,
        "tags": [],
        "units": [
            {
                "nid": "Kagerou",
                "team": "player",
                "ai": "None",
                "roam_ai": null,
                "ai_group": "",
                "starting_position": [
                    9,
                    12
                ],
                "starting_traveler": null,
                "generic": false
            },
            {
                "nid": "Reimu",
                "team": "player",
                "ai": "None",
                "roam_ai": null,
                "ai_group": "",
                "starting_position": [
                    10,
                    15
                ],
                "starting_traveler": null,
                "generic": false
            },
            {
                "nid": "Kasen",
                "team": "player",
                "ai": "None",
                "roam_ai": null,
                "ai_group": "",
                "starting_position": [
                    11,
                    13
                ],
                "starting_traveler": null,
                "generic": false
            },
            {
                "nid": "106",
                "variant": null,
                "level": 40,
                "klass": "Sage",
                "faction": "Youkai",
                "starting_items": [
                    [
                        "Fimbulvetr_2",
                        false
                    ]
                ],
                "starting_skills": [],
                "team": "enemy",
                "ai": "None",
                "roam_ai": null,
                "ai_group": "",
                "starting_position": [
                    4,
                    13
                ],
                "starting_traveler": null,
                "generic": true
            },
            {
                "nid": "Rumia",
                "team": "player",
                "ai": "None",
                "roam_ai": null,
                "ai_group": "",
                "starting_position": [
                    14,
                    12
                ],
                "starting_traveler": null,
                "generic": false
            },
            {
                "nid": "Wriggle",
                "team": "player",
                "ai": "None",
                "roam_ai": null,
                "ai_group": "",
                "starting_position": [
                    13,
                    12
                ],
                "starting_traveler": null,
                "generic": false
            },
            {
                "nid": "Aunn",
                "team": "player",
                "ai": "None",
                "roam_ai": null,
                "ai_group": "",
                "starting_position": [
                    20,
                    7
                ],
                "starting_traveler": null,
                "generic": false
            },
            {
                "nid": "Luna",
                "team": "player",
                "ai": "None",
                "roam_ai": null,
                "ai_group": "",
                "starting_position": [
                    1,
                    12
                ],
                "starting_traveler": null,
                "generic": false
            },
            {
                "nid": "Suika",
                "team": "player",
                "ai": "None",
                "roam_ai": null,
                "ai_group": "",
                "starting_position": [
                    10,
                    12
                ],
                "starting_traveler": null,
                "generic": false
            },
            {
                "nid": "Remilia",
                "team": "player",
                "ai": "None",
                "roam_ai": null,
                "ai_group": "",
                "starting_position": [
                    8,
                    12
                ],
                "starting_traveler": null,
                "generic": false
            },
            {
                "nid": "Tokiko",
                "team": "player",
                "ai": "None",
                "roam_ai": null,
                "ai_group": "",
                "starting_position": [
                    7,
                    12
                ],
                "starting_traveler": null,
                "generic": false
            },
            {
                "nid": "Letty",
                "team": "player",
                "ai": "None",
                "roam_ai": null,
                "ai_group": "",
                "starting_position": [
                    6,
                    12
                ],
                "starting_traveler": null,
                "generic": false
            },
            {
                "nid": "Kokoro",
                "team": "player",
                "ai": "None",
                "roam_ai": null,
                "ai_group": "",
                "starting_position": [
                    5,
                    12
                ],
                "starting_traveler": null,
                "generic": false
            },
            {
                "nid": "108",
                "variant": null,
                "level": 40,
                "klass": "Veteran_S",
                "faction": "Youkai",
                "starting_items": [
                    [
                        "War_Katana",
                        false
                    ]
                ],
                "starting_skills": [],
                "team": "enemy",
                "ai": "None",
                "roam_ai": null,
                "ai_group": "",
                "starting_position": [
                    5,
                    14
                ],
                "starting_traveler": null,
                "generic": true
            },
            {
                "nid": "109",
                "variant": null,
                "level": 40,
                "klass": "Veteran_A",
                "faction": "Youkai",
                "starting_items": [
                    [
                        "War_Club",
                        false
                    ]
                ],
                "starting_skills": [],
                "team": "enemy",
                "ai": "None",
                "roam_ai": null,
                "ai_group": "",
                "starting_position": [
                    6,
                    14
                ],
                "starting_traveler": null,
                "generic": true
            },
            {
                "nid": "112",
                "variant": null,
                "level": 40,
                "klass": "Spearmaster",
                "faction": "Youkai",
                "starting_items": [
                    [
                        "War_Yari",
                        false
                    ],
                    [
                        "Angelic_Robe",
                        false
                    ]
                ],
                "starting_skills": [],
                "team": "enemy",
                "ai": "Defend",
                "roam_ai": null,
                "ai_group": "",
                "starting_position": [
                    24,
                    7
                ],
                "starting_traveler": null,
                "generic": true
            },
            {
                "nid": "113",
                "variant": null,
                "level": 40,
                "klass": "Dracolord",
                "faction": "Youkai",
                "starting_items": [
                    [
                        "War_Yari",
                        false
                    ],
                    [
                        "Fimbulvetr",
                        false
                    ],
                    [
                        "War_Yumi",
                        false
                    ],
                    [
                        "Fenrir",
                        false
                    ]
                ],
                "starting_skills": [],
                "team": "player",
                "ai": "None",
                "roam_ai": null,
                "ai_group": "",
                "starting_position": [
                    8,
                    10
                ],
                "starting_traveler": null,
                "generic": true
            },
            {
                "nid": "116",
                "variant": null,
                "level": 40,
                "klass": "Dracolord",
                "faction": "Youkai",
                "starting_items": [
                    [
                        "War_Yari",
                        false
                    ],
                    [
                        "Fimbulvetr",
                        false
                    ],
                    [
                        "War_Yumi",
                        false
                    ],
                    [
                        "Fenrir",
                        false
                    ]
                ],
                "starting_skills": [],
                "team": "player",
                "ai": "None",
                "roam_ai": null,
                "ai_group": "",
                "starting_position": [
                    11,
                    10
                ],
                "starting_traveler": null,
                "generic": true
            },
            {
                "nid": "114",
                "variant": null,
                "level": 40,
                "klass": "Dracolord",
                "faction": "Youkai",
                "starting_items": [
                    [
                        "War_Katana",
                        false
                    ],
                    [
                        "Inquisition",
                        false
                    ],
                    [
                        "War_Club",
                        false
                    ],
                    [
                        "Skyward",
                        false
                    ]
                ],
                "starting_skills": [],
                "team": "player",
                "ai": "None",
                "roam_ai": null,
                "ai_group": "",
                "starting_position": [
                    12,
                    10
                ],
                "starting_traveler": null,
                "generic": true
            },
            {
                "nid": "118",
                "variant": null,
                "level": 40,
                "klass": "Dracolord",
                "faction": "Youkai",
                "starting_items": [
                    [
                        "War_Katana",
                        false
                    ],
                    [
                        "Killer_Bow",
                        false
                    ],
                    [
                        "War_Club",
                        false
                    ],
                    [
                        "Skyward",
                        false
                    ]
                ],
                "starting_skills": [],
                "team": "player",
                "ai": "None",
                "roam_ai": null,
                "ai_group": "",
                "starting_position": [
                    22,
                    9
                ],
                "starting_traveler": null,
                "generic": true
            },
            {
                "nid": "115",
                "variant": null,
                "level": 40,
                "klass": "Dracolord",
                "faction": "Youkai",
                "starting_items": [
                    [
                        "Brave_Sword",
                        false
                    ],
                    [
                        "Brave_Lance",
                        false
                    ],
                    [
                        "Brave_Axe",
                        false
                    ],
                    [
                        "Brave_Bow",
                        false
                    ]
                ],
                "starting_skills": [],
                "team": "player",
                "ai": "None",
                "roam_ai": null,
                "ai_group": "",
                "starting_position": [
                    7,
                    10
                ],
                "starting_traveler": null,
                "generic": true
            },
            {
                "nid": "117",
                "variant": null,
                "level": 40,
                "klass": "Dracolord",
                "faction": "Youkai",
                "starting_items": [
                    [
                        "Brave_Sword",
                        false
                    ],
                    [
                        "Brave_Lance",
                        false
                    ],
                    [
                        "Brave_Axe",
                        false
                    ],
                    [
                        "Brave_Bow",
                        false
                    ]
                ],
                "starting_skills": [],
                "team": "player",
                "ai": "None",
                "roam_ai": null,
                "ai_group": "",
                "starting_position": [
                    13,
                    10
                ],
                "starting_traveler": null,
                "generic": true
            },
            {
                "nid": "Marisa",
                "team": "player",
                "ai": "None",
                "roam_ai": null,
                "ai_group": "",
                "starting_position": [
                    8,
                    15
                ],
                "starting_traveler": null,
                "generic": false
            },
            {
                "nid": "Rinnosuke",
                "team": "player",
                "ai": "None",
                "roam_ai": null,
                "ai_group": "",
                "starting_position": [
                    9,
                    13
                ],
                "starting_traveler": null,
                "generic": false
            },
            {
                "nid": "Sunny",
                "team": "player",
                "ai": "None",
                "roam_ai": null,
                "ai_group": "",
                "starting_position": [
                    2,
                    11
                ],
                "starting_traveler": null,
                "generic": false
            },
            {
                "nid": "Star",
                "team": "player",
                "ai": "None",
                "roam_ai": null,
                "ai_group": "",
                "starting_position": [
                    1,
                    10
                ],
                "starting_traveler": null,
                "generic": false
            },
            {
                "nid": "Cirno",
                "team": "player",
                "ai": "None",
                "roam_ai": null,
                "ai_group": "",
                "starting_position": [
                    12,
                    15
                ],
                "starting_traveler": null,
                "generic": false
            },
            {
                "nid": "Daiyousei",
                "team": "player",
                "ai": "None",
                "roam_ai": null,
                "ai_group": "",
                "starting_position": [
                    21,
                    8
                ],
                "starting_traveler": null,
                "generic": false
            },
            {
                "nid": "Tewi",
                "team": "player",
                "ai": "None",
                "roam_ai": null,
                "ai_group": "",
                "starting_position": [
                    7,
                    16
                ],
                "starting_traveler": null,
                "generic": false
            },
            {
                "nid": "Reisen",
                "team": "player",
                "ai": "None",
                "roam_ai": null,
                "ai_group": "",
                "starting_position": [
                    6,
                    16
                ],
                "starting_traveler": null,
                "generic": false
            },
            {
                "nid": "Mokou",
                "team": "player",
                "ai": "None",
                "roam_ai": null,
                "ai_group": "",
                "starting_position": [
                    5,
                    16
                ],
                "starting_traveler": null,
                "generic": false
            },
            {
                "nid": "Kaguya",
                "team": "player",
                "ai": "None",
                "roam_ai": null,
                "ai_group": "",
                "starting_position": [
                    4,
                    16
                ],
                "starting_traveler": null,
                "generic": false
            },
            {
                "nid": "Seiran",
                "team": "player",
                "ai": "None",
                "roam_ai": null,
                "ai_group": "",
                "starting_position": [
                    3,
                    15
                ],
                "starting_traveler": null,
                "generic": false
            },
            {
                "nid": "Ringo",
                "team": "player",
                "ai": "None",
                "roam_ai": null,
                "ai_group": "",
                "starting_position": [
                    2,
                    15
                ],
                "starting_traveler": null,
                "generic": false
            },
            {
                "nid": "101",
                "variant": null,
                "level": 1,
                "klass": "Citizen",
                "faction": "Youkai",
                "starting_items": [
                    [
                        "Eye_of_Senri",
                        false
                    ]
                ],
                "starting_skills": [],
                "team": "player",
                "ai": "None",
                "roam_ai": null,
                "ai_group": "",
                "starting_position": [
                    9,
                    17
                ],
                "starting_traveler": null,
                "generic": true
            },
            {
                "nid": "102",
                "variant": null,
                "level": 1,
                "klass": "Citizen",
                "faction": "Youkai",
                "starting_items": [
                    [
                        "Iron_Sword",
                        false
                    ],
                    [
                        "Stone_Bowl",
                        false
                    ]
                ],
                "starting_skills": [],
                "team": "player",
                "ai": "None",
                "roam_ai": null,
                "ai_group": "",
                "starting_position": [
                    4,
                    17
                ],
                "starting_traveler": null,
                "generic": true
            },
            {
                "nid": "103",
                "variant": null,
                "level": 1,
                "klass": "Battlesage",
                "faction": "Youkai",
                "starting_items": [
                    [
                        "Iron_Sword",
                        false
                    ],
                    [
                        "Fire",
                        false
                    ]
                ],
                "starting_skills": [
                    "Weakened"
                ],
                "team": "player",
                "ai": "None",
                "roam_ai": null,
                "ai_group": "",
                "starting_position": [
                    20,
                    12
                ],
                "starting_traveler": null,
                "generic": true
            },
            {
                "nid": "Narumi",
                "team": "player",
                "ai": "None",
                "roam_ai": null,
                "ai_group": "",
                "starting_position": [
                    23,
                    9
                ],
                "starting_traveler": null,
                "generic": false
            },
            {
                "nid": "104",
                "variant": null,
                "level": 1,
                "klass": "Exorcist",
                "faction": "Youkai",
                "starting_items": [
                    [
                        "Sleep",
                        false
                    ],
                    [
                        "Ciggie_Box",
                        false
                    ]
                ],
                "starting_skills": [],
                "team": "player",
                "ai": "None",
                "roam_ai": null,
                "ai_group": "",
                "starting_position": [
                    9,
                    14
                ],
                "starting_traveler": null,
                "generic": true
            },
            {
                "nid": "Koakuma",
                "team": "player",
                "ai": "None",
                "roam_ai": null,
                "ai_group": "",
                "starting_position": [
                    8,
                    11
                ],
                "starting_traveler": null,
                "generic": false
            },
            {
                "nid": "105",
                "variant": null,
                "level": 1,
                "klass": "Citizen",
                "faction": "Youkai",
                "starting_items": [],
                "starting_skills": [
                    "Bleeding"
                ],
                "team": "enemy",
                "ai": "None",
                "roam_ai": null,
                "ai_group": "",
                "starting_position": [
                    8,
                    13
                ],
                "starting_traveler": null,
                "generic": true
            },
            {
                "nid": "110",
                "variant": null,
                "level": 1,
                "klass": "Citizen",
                "faction": "Youkai",
                "starting_items": [],
                "starting_skills": [
                    "Bleeding"
                ],
                "team": "enemy",
                "ai": "None",
                "roam_ai": null,
                "ai_group": "",
                "starting_position": [
                    15,
                    13
                ],
                "starting_traveler": null,
                "generic": true
            },
            {
                "nid": "111",
                "variant": null,
                "level": 1,
                "klass": "Citizen",
                "faction": "Youkai",
                "starting_items": [],
                "starting_skills": [
                    "Bleeding"
                ],
                "team": "enemy",
                "ai": "None",
                "roam_ai": null,
                "ai_group": "",
                "starting_position": [
                    16,
                    12
                ],
                "starting_traveler": null,
                "generic": true
            },
            {
                "nid": "119",
                "variant": null,
                "level": 1,
                "klass": "Citizen",
                "faction": "Youkai",
                "starting_items": [],
                "starting_skills": [
                    "Bleeding"
                ],
                "team": "enemy",
                "ai": "None",
                "roam_ai": null,
                "ai_group": "",
                "starting_position": [
                    17,
                    13
                ],
                "starting_traveler": null,
                "generic": true
            },
            {
                "nid": "120",
                "variant": null,
                "level": 1,
                "klass": "Citizen",
                "faction": "Youkai",
                "starting_items": [],
                "starting_skills": [
                    "Bleeding"
                ],
                "team": "enemy",
                "ai": "None",
                "roam_ai": null,
                "ai_group": "",
                "starting_position": [
                    18,
                    14
                ],
                "starting_traveler": null,
                "generic": true
            },
            {
                "nid": "107",
                "variant": null,
                "level": 1,
                "klass": "Citizen",
                "faction": "Youkai",
                "starting_items": [],
                "starting_skills": [
                    "Bleeding"
                ],
                "team": "enemy",
                "ai": "None",
                "roam_ai": null,
                "ai_group": "",
                "starting_position": [
                    7,
                    13
                ],
                "starting_traveler": null,
                "generic": true
            },
            {
                "nid": "Sakuya",
                "team": "player",
                "ai": "None",
                "roam_ai": null,
                "ai_group": "",
                "starting_position": [
                    6,
                    13
                ],
                "starting_traveler": null,
                "generic": false
            },
            {
                "nid": "Youmu",
                "team": "player",
                "ai": "None",
                "roam_ai": null,
                "ai_group": "",
                "starting_position": [
                    11,
                    16
                ],
                "starting_traveler": null,
                "generic": false
            },
            {
                "nid": "Kogasa",
                "team": "player",
                "ai": "None",
                "roam_ai": null,
                "ai_group": "",
                "starting_position": [
                    13,
                    14
                ],
                "starting_traveler": null,
                "generic": false
            },
            {
                "nid": "Rumia_Boss",
                "team": "enemy",
                "ai": "None",
                "roam_ai": null,
                "ai_group": "",
                "starting_position": [
                    9,
                    16
                ],
                "starting_traveler": null,
                "generic": false
            },
            {
                "nid": "SigmaRaven",
                "team": "player",
                "ai": "None",
                "roam_ai": null,
                "ai_group": "",
                "starting_position": [
                    14,
                    17
                ],
                "starting_traveler": null,
                "generic": false
            },
            {
                "nid": "121",
                "variant": null,
                "level": 40,
                "klass": "Warden",
                "faction": "Youkai",
                "starting_items": [],
                "starting_skills": [],
                "team": "enemy",
                "ai": "None",
                "roam_ai": null,
                "ai_group": "",
                "starting_position": [
                    23,
                    6
                ],
                "starting_traveler": null,
                "generic": true
            }
        ],
        "regions": [
            {
                "nid": "Armory",
                "region_type": "event",
                "position": [
                    5,
                    7
                ],
                "size": [
                    1,
                    1
                ],
                "sub_nid": "Armory",
                "condition": "True",
                "time_left": null,
                "only_once": false,
                "interrupt_move": false,
                "hide_time": false
            },
            {
                "nid": "Door1",
                "region_type": "event",
                "position": [
                    4,
                    2
                ],
                "size": [
                    1,
                    1
                ],
                "sub_nid": "Door",
                "condition": "unit.can_unlock(region)",
                "time_left": null,
                "only_once": true,
                "interrupt_move": false,
                "hide_time": false
            }
        ],
        "unit_groups": [],
        "ai_groups": [
            {
                "nid": "",
                "trigger_threshold": 1
            }
        ]
    }
]