[
    {
        "name": "Door_5",
        "trigger": "Door",
        "level_nid": "4",
        "condition": "region.nid == 'Door_1'",
        "commands": [],
        "only_once": true,
        "priority": 20,
        "_source": [
            "unlock;{unit}",
            "show_layer;Door5",
            "add_portrait;{unit};Left",
            "speak;{unit};Alright! You're all free now!",
            "add_portrait;Man1;Right",
            "speak;Man1;...",
            "remove_portrait;Man1",
            "speak;{unit};What a weirdo.",
            "add_portrait;Cirno;CenterRight",
            "add_portrait;Daiyousei;FarRight",
            "speak;Cirno;Aha! I knew we'd be free, Dai!",
            "speak;Daiyousei;Good thing we were lucky...",
            "speak;Cirno;Luck shmuck, let's get outta here!",
            "multi_remove_portrait;{unit};Cirno;Daiyousei",
            "change_ai;Cirno;GreenEscape",
            "change_ai;Daiyousei;GreenEscape",
            "change_ai;145;GreenEscape",
            "change_ai;146;GreenEscape",
            "change_ai;147;GreenEscape"
        ]
    }
]